static/__init__.py
static/static.py
midastoolpy-0.0.1.dist-info/LICENSE
midastoolpy-0.0.1.dist-info/METADATA
midastoolpy-0.0.1.dist-info/WHEEL
midastoolpy-0.0.1.dist-info/top_level.txt
midastoolpy-0.0.1.dist-info/RECORD
